LICENSE.txt
setup.cfg
setup.py
sweelimiter/__init__.py
sweelimiter.egg-info/PKG-INFO
sweelimiter.egg-info/SOURCES.txt
sweelimiter.egg-info/dependency_links.txt
sweelimiter.egg-info/requires.txt
sweelimiter.egg-info/top_level.txt
sweelimiter/api/__init__.py
sweelimiter/api/backend.py
sweelimiter/api/bypass_checker.py
sweelimiter/api/error_handler.py
sweelimiter/api/interval.py
sweelimiter/api/key_extractor.py
sweelimiter/api/limit_config.py
sweelimiter/api/limiter.py
sweelimiter/api/limiter_engine.py
sweelimiter/api/limiter_result.py
sweelimiter/api/frontend/__init__.py
sweelimiter/api/frontend/decorator.py
sweelimiter/api/frontend/depends.py
sweelimiter/api/frontend/middleware.py
sweelimiter/backends/__init__.py
sweelimiter/backends/asyncio_redis_backend.py
sweelimiter/backends/redis_backend.py
sweelimiter/extractors/__init__.py
sweelimiter/extractors/host_extractor.py